pyAsyncBot-0.6.0.data/scripts/pyasyncbotd
pyasyncbot/Bot.py
pyasyncbot/BotConfig.py
pyasyncbot/CommunicationWare.py
pyasyncbot/Contacts.py
pyasyncbot/Event.py
pyasyncbot/FrameworkWrapper.py
pyasyncbot/Message.py
pyasyncbot/MsgContent.py
pyasyncbot/__init__.py
pyasyncbot/commu/CommunicationBackend.py
pyasyncbot/commu/__init__.py
pyasyncbot/commu/http.py
pyasyncbot/commu/websocket.py
pyasyncbot/daemon/__init__.py
pyasyncbot/proto/MyBotProtocol.py
pyasyncbot/proto/Protocol.py
pyasyncbot/proto/__init__.py
pyAsyncBot-0.6.0.dist-info/METADATA
pyAsyncBot-0.6.0.dist-info/WHEEL
pyAsyncBot-0.6.0.dist-info/top_level.txt
pyAsyncBot-0.6.0.dist-info/RECORD
