Metadata-Version: 2.1
Name: pyAsyncBot
Version: 0.6.0
Summary: An async chat bot client framework
Home-page: UNKNOWN
Author: SalimTerryLi
License: MIT
Platform: UNKNOWN
Requires-Dist: ujson (>=5.1.0)
Requires-Dist: asyncio (>=3.4.3)
Requires-Dist: aiohttp (>=3.8.1)
Requires-Dist: aiofiles (>=0.8.0)
Requires-Dist: loguru (>=0.6.0)
